schumacher/__init__.py
schumacher/datasets/__init__.py
schumacher/image_extraction/__init__.py
schumacher/image_extraction/bipartite.py
schumacher/ocr/__init__.py
schumacher/ocr/train/__init__.py
schumacher/utils/__init__.py
schumacher/utils/image_processor.py
schumacher/utils/unpack_folder.sh
schumacher-0.1.0.dist-info/METADATA
schumacher-0.1.0.dist-info/WHEEL
schumacher-0.1.0.dist-info/RECORD
