Metadata-Version: 2.1
Name: schumacher
Version: 0.1.0
Summary: 
Author: Nikita
Requires-Python: >=3.10,<4.0
Classifier: Programming Language :: Python :: 3
Classifier: Programming Language :: Python :: 3.10
Classifier: Programming Language :: Python :: 3.11
Classifier: Programming Language :: Python :: 3.12
Requires-Dist: datasets (>=2.17.1,<3.0.0)
